aexaroton/__init__.py
aexaroton/client.py
aexaroton/errors.py
aexaroton/server.py
aexaroton/socket_types.py
aexaroton/types.py
aexaroton/websocket.py
aexaroton-0.2.0.dist-info/WHEEL
aexaroton-0.2.0.dist-info/METADATA
aexaroton-0.2.0.dist-info/RECORD
