Metadata-Version: 2.4
Name: aexaroton
Version: 0.2.0
Summary: An async exaroton api wrapper
Author: StarrFox
Author-email: StarrFox <StarrFox6312@gmail.com>
License-Expression: MIT
Requires-Dist: aiohttp>=3.11.11,<4
Requires-Dist: yarl>=1.18.3,<2
Requires-Dist: pydantic>=2.10.5,<3
Requires-Python: >=3.11
